Workbook

Sheet Cover
B3: PROFYT
B6: Margin Waterfall Analysis
B7: Client Input Template — Tier 2 · Tool 4
B10: Step 1 — Enter 8 quarters of P&L data in the P&L Inputs tab — Q1 = oldest, Q8 = most recent.
B11: Step 2 — Complete the Below-the-Line tab for interest, tax, and one-off items.
B12: Step 3 — All monetary values in ₹ Crore. Expenses as positive numbers.
B13: Step 4 — If a line is zero for a quarter, enter 0 — do not leave blanks.
B14: Step 5 — EBITDA and EBIT are auto-calculated — do not override them.
B16: Yellow cell — enter your data here
B17: Grey cell — auto-calculated, do not edit
B18: Green text — linked from another sheet

Sheet P&L Inputs
B1: P&L Inputs — 8 Quarters (₹ Crore)
B2: All values in ₹ Crore. Expenses as positive numbers.
B3: Line Item | C3: Q1 (oldest) | D3: Q2 | E3: Q3 | F3: Q4 | G3: Q5 | H3: Q6 | I3: Q7 | J3: Q8 (latest)
B4: REVENUE
B5: Product / SaaS Revenue | C5: 0 | D5: 0 | E5: 0 | F5: 0 | G5: 0 | H5: 0 | I5: 0 | J5: 0 | K5: Primary product or SaaS subscription revenue
B6: Services / Implementation Revenue | C6: 0 | D6: 0 | E6: 0 | F6: 0 | G6: 0 | H6: 0 | I6: 0 | J6: 0 | K6: Professional services, implementation, training
B7: Other Revenue | C7: 0 | D7: 0 | E7: 0 | F7: 0 | G7: 0 | H7: 0 | I7: 0 | J7: 0 | K7: Any other operating revenue
B8: TOTAL REVENUE | C8: =SUM(C5:C7) -> 0 | D8: =SUM(D5:D7) -> 0 | E8: =SUM(E5:E7) -> 0 | F8: =SUM(F5:F7) -> 0 | G8: =SUM(G5:G7) -> 0 | H8: =SUM(H5:H7) -> 0 | I8: =SUM(I5:I7) -> 0 | J8: =SUM(J5:J7) -> 0
B9: COST OF REVENUE
B10: Direct Labour / Delivery Costs | C10: 0 | D10: 0 | E10: 0 | F10: 0 | G10: 0 | H10: 0 | I10: 0 | J10: 0 | K10: Costs directly tied to delivering the product/service
B11: Cloud & Infrastructure COGS | C11: 0 | D11: 0 | E11: 0 | F11: 0 | G11: 0 | H11: 0 | I11: 0 | J11: 0 | K11: Hosting, API costs directly attributable to revenue
B12: Materials & Third-Party Costs | C12: 0 | D12: 0 | E12: 0 | F12: 0 | G12: 0 | H12: 0 | I12: 0 | J12: 0 | K12: Materials, outsourced delivery, direct pass-through costs
B13: TOTAL COGS | C13: =SUM(C10:C12) -> 0 | D13: =SUM(D10:D12) -> 0 | E13: =SUM(E10:E12) -> 0 | F13: =SUM(F10:F12) -> 0 | G13: =SUM(G10:G12) -> 0 | H13: =SUM(H10:H12) -> 0 | I13: =SUM(I10:I12) -> 0 | J13: =SUM(J10:J12) -> 0
B14: GROSS PROFIT | C14: =IFERROR(C8-C13,0) -> 0 | D14: =IFERROR(D8-D13,0) -> 0 | E14: =IFERROR(E8-E13,0) -> 0 | F14: =IFERROR(F8-F13,0) -> 0 | G14: =IFERROR(G8-G13,0) -> 0 | H14: =IFERROR(H8-H13,0) -> 0 | I14: =IFERROR(I8-I13,0) -> 0 | J14: =IFERROR(J8-J13,0) -> 0
B15: GROSS MARGIN % | C15: =IFERROR(C14/C8,0) -> 0 | D15: =IFERROR(D14/D8,0) -> 0 | E15: =IFERROR(E14/E8,0) -> 0 | F15: =IFERROR(F14/F8,0) -> 0 | G15: =IFERROR(G14/G8,0) -> 0 | H15: =IFERROR(H14/H8,0) -> 0 | I15: =IFERROR(I14/I8,0) -> 0 | J15: =IFERROR(J14/J8,0) -> 0
B16: OPERATING EXPENSES
B17: Research & Development | C17: 0 | D17: 0 | E17: 0 | F17: 0 | G17: 0 | H17: 0 | I17: 0 | J17: 0 | K17: Engineering salaries, R&D tools, product costs
B18: Sales & Marketing | C18: 0 | D18: 0 | E18: 0 | F18: 0 | G18: 0 | H18: 0 | I18: 0 | J18: 0 | K18: All sales and marketing costs including people
B19: General & Administrative | C19: 0 | D19: 0 | E19: 0 | F19: 0 | G19: 0 | H19: 0 | I19: 0 | J19: 0 | K19: G&A — finance, legal, HR, admin, office
B20: TOTAL OPEX | C20: =SUM(C17:C19) -> 0 | D20: =SUM(D17:D19) -> 0 | E20: =SUM(E17:E19) -> 0 | F20: =SUM(F17:F19) -> 0 | G20: =SUM(G17:G19) -> 0 | H20: =SUM(H17:H19) -> 0 | I20: =SUM(I17:I19) -> 0 | J20: =SUM(J17:J19) -> 0
B21: EBITDA | C21: =IFERROR(C14-C20,0) -> 0 | D21: =IFERROR(D14-D20,0) -> 0 | E21: =IFERROR(E14-E20,0) -> 0 | F21: =IFERROR(F14-F20,0) -> 0 | G21: =IFERROR(G14-G20,0) -> 0 | H21: =IFERROR(H14-H20,0) -> 0 | I21: =IFERROR(I14-I20,0) -> 0 | J21: =IFERROR(J14-J20,0) -> 0
B22: EBITDA MARGIN % | C22: =IFERROR(C21/C8,0) -> 0 | D22: =IFERROR(D21/D8,0) -> 0 | E22: =IFERROR(E21/E8,0) -> 0 | F22: =IFERROR(F21/F8,0) -> 0 | G22: =IFERROR(G21/G8,0) -> 0 | H22: =IFERROR(H21/H8,0) -> 0 | I22: =IFERROR(I21/I8,0) -> 0 | J22: =IFERROR(J21/J8,0) -> 0
B23: D&A
B24: Depreciation | C24: 0 | D24: 0 | E24: 0 | F24: 0 | G24: 0 | H24: 0 | I24: 0 | J24: 0 | K24: Fixed asset depreciation
B25: Amortisation | C25: 0 | D25: 0 | E25: 0 | F25: 0 | G25: 0 | H25: 0 | I25: 0 | J25: 0 | K25: Intangible amortisation (incl. capitalised software)
B26: TOTAL D&A | C26: =IFERROR(C24+C25,0) -> 0 | D26: =IFERROR(D24+D25,0) -> 0 | E26: =IFERROR(E24+E25,0) -> 0 | F26: =IFERROR(F24+F25,0) -> 0 | G26: =IFERROR(G24+G25,0) -> 0 | H26: =IFERROR(H24+H25,0) -> 0 | I26: =IFERROR(I24+I25,0) -> 0 | J26: =IFERROR(J24+J25,0) -> 0
B27: EBIT | C27: =IFERROR(C21-C26,0) -> 0 | D27: =IFERROR(D21-D26,0) -> 0 | E27: =IFERROR(E21-E26,0) -> 0 | F27: =IFERROR(F21-F26,0) -> 0 | G27: =IFERROR(G21-G26,0) -> 0 | H27: =IFERROR(H21-H26,0) -> 0 | I27: =IFERROR(I21-I26,0) -> 0 | J27: =IFERROR(J21-J26,0) -> 0
B28: EBIT MARGIN % | C28: =IFERROR(C27/C8,0) -> 0 | D28: =IFERROR(D27/D8,0) -> 0 | E28: =IFERROR(E27/E8,0) -> 0 | F28: =IFERROR(F27/F8,0) -> 0 | G28: =IFERROR(G27/G8,0) -> 0 | H28: =IFERROR(H27/H8,0) -> 0 | I28: =IFERROR(I27/I8,0) -> 0 | J28: =IFERROR(J27/J8,0) -> 0

Sheet Below-the-Line
B1: Below-the-Line Items — 8 Quarters
B2: Interest, tax, one-off items. All positive numbers.
B3: Line Item | C3: Q1 (oldest) | D3: Q2 | E3: Q3 | F3: Q4 | G3: Q5 | H3: Q6 | I3: Q7 | J3: Q8 (latest)
B4: Interest Income | C4: 0 | D4: 0 | E4: 0 | F4: 0 | G4: 0 | H4: 0 | I4: 0 | J4: 0 | K4: Interest earned on cash/FDs
B5: Interest Expense | C5: 0 | D5: 0 | E5: 0 | F5: 0 | G5: 0 | H5: 0 | I5: 0 | J5: 0 | K5: Interest paid on all loans and credit facilities
B6: Other Finance Income / (Costs) | C6: 0 | D6: 0 | E6: 0 | F6: 0 | G6: 0 | H6: 0 | I6: 0 | J6: 0 | K6: FX gains, investment income, other finance items
B7: PBT (Profit Before Tax) | C7: =IFERROR('P&L Inputs'!C27+C4-C5+C6,0) -> 0 | D7: =IFERROR('P&L Inputs'!D27+D4-D5+D6,0) -> 0 | E7: =IFERROR('P&L Inputs'!E27+E4-E5+E6,0) -> 0 | F7: =IFERROR('P&L Inputs'!F27+F4-F5+F6,0) -> 0 | G7: =IFERROR('P&L Inputs'!G27+G4-G5+G6,0) -> 0 | H7: =IFERROR('P&L Inputs'!H27+H4-H5+H6,0) -> 0 | I7: =IFERROR('P&L Inputs'!I27+I4-I5+I6,0) -> 0 | J7: =IFERROR('P&L Inputs'!J27+J4-J5+J6,0) -> 0
B8: Income Tax (Current) | C8: 0 | D8: 0 | E8: 0 | F8: 0 | G8: 0 | H8: 0 | I8: 0 | J8: 0 | K8: Advance tax, TDS, current year tax provision
B9: Deferred Tax Adjustment | C9: 0 | D9: 0 | E9: 0 | F9: 0 | G9: 0 | H9: 0 | I9: 0 | J9: 0 | K9: Net deferred tax asset/liability movement
B10: PAT (Profit After Tax) | C10: =IFERROR(C7-C8-C9,0) -> 0 | D10: =IFERROR(D7-D8-D9,0) -> 0 | E10: =IFERROR(E7-E8-E9,0) -> 0 | F10: =IFERROR(F7-F8-F9,0) -> 0 | G10: =IFERROR(G7-G8-G9,0) -> 0 | H10: =IFERROR(H7-H8-H9,0) -> 0 | I10: =IFERROR(I7-I8-I9,0) -> 0 | J10: =IFERROR(J7-J8-J9,0) -> 0
B11: PAT MARGIN % | C11: =IFERROR(C10/'P&L Inputs'!C8,0) -> 0 | D11: =IFERROR(D10/'P&L Inputs'!D8,0) -> 0 | E11: =IFERROR(E10/'P&L Inputs'!E8,0) -> 0 | F11: =IFERROR(F10/'P&L Inputs'!F8,0) -> 0 | G11: =IFERROR(G10/'P&L Inputs'!G8,0) -> 0 | H11: =IFERROR(H10/'P&L Inputs'!H8,0) -> 0 | I11: =IFERROR(I10/'P&L Inputs'!I8,0) -> 0 | J11: =IFERROR(J10/'P&L Inputs'!J8,0) -> 0
B13: One-Off Items (Exceptional) | C13: 0 | D13: 0 | E13: 0 | F13: 0 | G13: 0 | H13: 0 | I13: 0 | J13: 0 | K13: Restructuring costs, asset write-offs, one-time charges — for normalisation
B14: Normalised PAT | C14: =IFERROR(C10-C13,0) -> 0 | D14: =IFERROR(D10-D13,0) -> 0 | E14: =IFERROR(E10-E13,0) -> 0 | F14: =IFERROR(F10-F13,0) -> 0 | G14: =IFERROR(G10-G13,0) -> 0 | H14: =IFERROR(H10-H13,0) -> 0 | I14: =IFERROR(I10-I13,0) -> 0 | J14: =IFERROR(J10-J13,0) -> 0
B15: Normalised PAT Margin % | C15: =IFERROR(C14/'P&L Inputs'!C8,0) -> 0 | D15: =IFERROR(D14/'P&L Inputs'!D8,0) -> 0 | E15: =IFERROR(E14/'P&L Inputs'!E8,0) -> 0 | F15: =IFERROR(F14/'P&L Inputs'!F8,0) -> 0 | G15: =IFERROR(G14/'P&L Inputs'!G8,0) -> 0 | H15: =IFERROR(H14/'P&L Inputs'!H8,0) -> 0 | I15: =IFERROR(I14/'P&L Inputs'!I8,0) -> 0 | J15: =IFERROR(J14/'P&L Inputs'!J8,0) -> 0
